[
  {
    "question": "Where can I find information on obtaining Arbutus Object Storage?",
    "answer": "For information on obtaining Arbutus Object Storage, please see the page linked as 'this page'."
  },
  {
    "question": "How do you manage an Arbutus object store using a client?",
    "answer": "To manage your Arbutus object store, you need to choose an object storage client and follow the instructions provided on the corresponding linked pages."
  },
  {
    "question": "What are some of the object storage clients that can be used to access Arbutus object storage?",
    "answer": "Clients mentioned for accessing Arbutus object storage include s3cmd, WinSCP, AWS CLI, and Globus."
  },
  {
    "question": "Does Arbutus' Object Storage solution use Amazon's S3 Virtual Hosting?",
    "answer": "No, Arbutus' Object Storage solution does not use Amazon's S3 Virtual Hosting."
  },
  {
    "question": "What is S3 Virtual Hosting also referred to as?",
    "answer": "S3 Virtual Hosting is also referred to as the DNS-based bucket approach."
  },
  {
    "question": "What do object storage clients assume by default regarding S3 Virtual Hosting when connecting to Arbutus Object Storage?",
    "answer": "Object storage clients assume the S3 Virtual Hosting (DNS-based bucket) approach by default."
  },
  {
    "question": "How should clients be configured when connecting to Arbutus Object Storage, given it does not use S3 Virtual Hosting?",
    "answer": "Clients need to be configured not to use the S3 Virtual Hosting approach, as described in the linked pages."
  }
]