[
  {
    "question": "What is the address for the Cedar cloud?",
    "answer": "The address for the Cedar cloud is http://cedar.cloud.alliancecan.ca."
  },
  {
    "question": "Where is the Cedar cloud located?",
    "answer": "The Cedar cloud is located at Simon Fraser University."
  },
  {
    "question": "What is the total number of CPUs in the Cedar cloud?",
    "answer": "The Cedar cloud has a total of 1,024 CPUs."
  },
  {
    "question": "How much total RAM does the Cedar cloud possess?",
    "answer": "The Cedar cloud has a total of 7,680 GB of RAM."
  },
  {
    "question": "What is the persistent Ceph storage capacity for the Cedar cloud?",
    "answer": "The Cedar cloud has 500 TB of persistent Ceph storage."
  },
  {
    "question": "What kind of CPUs are used in the 28-node configuration of the Cedar cloud?",
    "answer": "The 28-node configuration in the Cedar cloud uses 2 x E5-2683 v4 CPUs per node."
  },
  {
    "question": "What is the local storage configuration for the 28-node cluster in the Cedar cloud?",
    "answer": "The local storage for the 28-node cluster in the Cedar cloud consists of 2 x 480GB SSDs in RAID1."
  },
  {
    "question": "What is the address for the Graham cloud?",
    "answer": "The address for the Graham cloud is https://graham.cloud.alliancecan.ca."
  },
  {
    "question": "Where is the Graham cloud situated?",
    "answer": "The Graham cloud is located at the University of Waterloo."
  },
  {
    "question": "What is the total CPU count for the Graham cloud?",
    "answer": "The Graham cloud has a total of 1,368 CPUs."
  },
  {
    "question": "How much total RAM is available in the Graham cloud?",
    "answer": "The Graham cloud has a total of 15,616 GB of RAM."
  },
  {
    "question": "What is the persistent Ceph storage capacity for the Graham cloud?",
    "answer": "The Graham cloud has 84 TB of persistent Ceph storage."
  },
  {
    "question": "What CPU model and memory configuration is found in the 6-node cluster of the Graham cloud?",
    "answer": "The 6-node cluster in the Graham cloud features 2 x E5-2683 v4 CPUs and 256 GB of memory per node."
  },
  {
    "question": "Which cluster in the Graham cloud uses 2 x Xeon(R) Gold 6130 CPUs?",
    "answer": "The 8-node cluster in the Graham cloud uses 2 x Xeon(R) Gold 6130 CPUs."
  },
  {
    "question": "What is the local storage setup for the 12-node cluster in the Graham cloud?",
    "answer": "The 12-node cluster in the Graham cloud uses 2x 1TB SSD in RAID0 for local storage."
  },
  {
    "question": "What is the address for the B\u00e9luga cloud?",
    "answer": "The address for the B\u00e9luga cloud is https://beluga.cloud.alliancecan.ca."
  },
  {
    "question": "Where is the B\u00e9luga cloud located?",
    "answer": "The B\u00e9luga cloud is located at \u00c9cole de Technologie Sup\u00e9rieure."
  },
  {
    "question": "What is the total number of vCPUs in the B\u00e9luga cloud?",
    "answer": "The B\u00e9luga cloud has a total of 7,168 vCPUs."
  },
  {
    "question": "What is the total RAM capacity in the B\u00e9luga cloud?",
    "answer": "The B\u00e9luga cloud has a total of 36,864 GiB of RAM."
  },
  {
    "question": "What types and capacities of persistent Ceph storage are available in the B\u00e9luga cloud?",
    "answer": "The B\u00e9luga cloud offers 200 TiB of replicated persistent SSD Ceph storage and 1.7 PiB of erasure coded persistent HDD Ceph storage."
  },
  {
    "question": "What CPU model is used across the nodes in the B\u00e9luga cloud?",
    "answer": "All nodes in the B\u00e9luga cloud use 2 x Intel Xeon Gold 5218 CPUs."
  },
  {
    "question": "How is ephemeral storage handled in the B\u00e9luga cloud?",
    "answer": "Ephemeral storage in the B\u00e9luga cloud is not local but is provided in Ceph."
  },
  {
    "question": "What is the interconnect speed for B\u00e9luga cloud nodes?",
    "answer": "B\u00e9luga cloud nodes use a 1 x 25GbE interconnect."
  },
  {
    "question": "What is the memory configuration for the 96-node cluster in the B\u00e9luga cloud?",
    "answer": "Each node in the 96-node cluster of the B\u00e9luga cloud has 256 GB of memory."
  }
]