[
  {
    "question": "What versions are available for mdacli?",
    "answer": "Version 0.1.19 is available for mdacli."
  },
  {
    "question": "What is the version for mdahole2?",
    "answer": "The version available for mdahole2 is 0.5.0."
  },
  {
    "question": "List all available versions for MDAnalysis.",
    "answer": "The available versions for MDAnalysis are 2.7.0, 2.6.0, 2.4.3, 2.4.2, 2.4.1, 2.3.0, 2.2.0, 2.0.0, and 1.0.0."
  },
  {
    "question": "What is the latest version of MDAnalysis?",
    "answer": "The latest version of MDAnalysis listed is 2.7.0."
  },
  {
    "question": "What versions of MDAnalysisTests are provided?",
    "answer": "MDAnalysisTests is available in versions 2.9.0, 2.7.0, 2.6.0, 2.4.3, 2.4.2, 2.4.1, 2.3.0, 2.2.0, 2.0.0, 1.1.1, 1.0.0, 0.19.2, 0.18.0, and 0.17.0."
  },
  {
    "question": "What's the newest version of MDAnalysisTests?",
    "answer": "The newest version of MDAnalysisTests is 2.9.0."
  },
  {
    "question": "Can you tell me the versions for mdbenchmark?",
    "answer": "mdbenchmark has versions 1.3.1 and 1.3.0."
  },
  {
    "question": "What are the versions of mdit_py_plugins?",
    "answer": "The versions for mdit_py_plugins are 0.4.2, 0.4.1, 0.3.4, and 0.3.0."
  },
  {
    "question": "Show me the versions available for mdolab_baseclasses.",
    "answer": "mdolab_baseclasses is available in versions 1.8.2, 1.8.1, and 1.7.0."
  },
  {
    "question": "Which version of mdsynthesis is listed?",
    "answer": "mdsynthesis is listed with version 0.6.1."
  },
  {
    "question": "What versions does mdtraj have?",
    "answer": "mdtraj has versions 1.9.7 and 1.9.6."
  },
  {
    "question": "List the versions for mdurl.",
    "answer": "The versions for mdurl are 0.1.2 and 0.1.1."
  },
  {
    "question": "What version of MEAutility is available?",
    "answer": "Version 1.4.8 of MEAutility is available."
  },
  {
    "question": "What are the available versions for medaka?",
    "answer": "medaka is available in versions 1.8.1, 1.7.3, 1.7.0, 1.6.0, 1.5.0, 0.12.1, and 0.3.0."
  },
  {
    "question": "What is the highest version of medaka?",
    "answer": "The highest version of medaka listed is 1.8.1."
  },
  {
    "question": "Is mediapipe available, and if so, which version?",
    "answer": "Yes, mediapipe is available in version 0.9.0."
  },
  {
    "question": "What's the version for mediapy?",
    "answer": "The version for mediapy is 1.2.0."
  },
  {
    "question": "Which version of MedPy is listed?",
    "answer": "MedPy is listed with version 0.4.0."
  },
  {
    "question": "What version does megalodon have?",
    "answer": "megalodon has version 2.5.0."
  },
  {
    "question": "Are there any versions listed for memoization?",
    "answer": "Yes, memoization is listed with version 0.4.0."
  },
  {
    "question": "What is the available version of memory_maze?",
    "answer": "The available version of memory_maze is 1.0.3."
  },
  {
    "question": "Which versions of memory_profiler are available?",
    "answer": "memory_profiler is available in versions 0.61.0 and 0.52.0."
  },
  {
    "question": "Is mendeleev available, and what is its version?",
    "answer": "Yes, mendeleev is available in version 0.5.2."
  },
  {
    "question": "What version of MeneTools is listed?",
    "answer": "MeneTools is listed with version 3.3.0."
  },
  {
    "question": "Which version does mercantile have?",
    "answer": "mercantile has version 1.2.1."
  },
  {
    "question": "What is the version for mercurial?",
    "answer": "The version for mercurial is 5.8.1."
  },
  {
    "question": "List the version for mergedeep.",
    "answer": "mergedeep is available in version 1.3.4."
  },
  {
    "question": "What versions of merlinquantum are listed?",
    "answer": "merlinquantum is listed with version 0.1.2."
  },
  {
    "question": "Is Mesa available, and if so, what version?",
    "answer": "Yes, Mesa is available in version 0.8.9."
  },
  {
    "question": "What are the versions for mescal?",
    "answer": "mescal has versions 1.1.3 and 1.1.2."
  },
  {
    "question": "List all versions for meshio.",
    "answer": "The versions for meshio are 5.3.4, 5.0.0, 4.0.16, and 4.0.15."
  },
  {
    "question": "What versions of meson are available?",
    "answer": "meson is available in versions 1.9.1, 1.9.0, 1.8.2, 1.7.0, 1.6.1, 1.5.1, 1.4.1, 1.2.2, 1.2.1, 1.2.0, 1.1.1, 1.0.1, 1.0.0, and 0.64.0."
  },
  {
    "question": "What is the most recent version of meson?",
    "answer": "The most recent version of meson is 1.9.1."
  },
  {
    "question": "Which versions of meson_python are listed?",
    "answer": "meson_python is listed with versions 0.18.0, 0.17.1, 0.16.0, 0.14.0, 0.13.2, 0.12.1, and 0.10.0."
  },
  {
    "question": "What's the latest version for meson_python?",
    "answer": "The latest version for meson_python is 0.18.0."
  },
  {
    "question": "What version of metabolisHMM is available?",
    "answer": "metabolisHMM is available in version 2.22."
  },
  {
    "question": "What is the version for MetaCHIP?",
    "answer": "The version for MetaCHIP is 1.10.5."
  },
  {
    "question": "Which version of Metage2Metabo is listed?",
    "answer": "Metage2Metabo is listed with version 1.5.3."
  },
  {
    "question": "What versions of metakernel are available?",
    "answer": "metakernel is available in versions 0.30.2 and 0.27.5."
  },
  {
    "question": "List all available versions for MetaPhlAn.",
    "answer": "The available versions for MetaPhlAn are 4.1.1, 4.0.6, 4.0.3, 3.0.7, and 3.0.0a1."
  },
  {
    "question": "What is the version for meteor?",
    "answer": "The version for meteor is 2.0.18."
  },
  {
    "question": "What version of metomi_isodatetime is available?",
    "answer": "metomi_isodatetime is available in version 1!3.0.0."
  },
  {
    "question": "Which version of metomi_rose is listed?",
    "answer": "metomi_rose is listed with version 2.1.0."
  },
  {
    "question": "What version does MetPy have?",
    "answer": "MetPy has version 1.0."
  },
  {
    "question": "What is the available version of metsim?",
    "answer": "The available version of metsim is 2.4.1."
  },
  {
    "question": "Which version of miceforest is listed?",
    "answer": "miceforest is listed with version 5.6.3."
  },
  {
    "question": "What version does microviewer have?",
    "answer": "microviewer has version 1.10.0."
  },
  {
    "question": "What is the version for MIDASpy?",
    "answer": "The version for MIDASpy is 1.2.3."
  },
  {
    "question": "Which version of miditok is available?",
    "answer": "miditok is available in version 3.0.4."
  },
  {
    "question": "What version does miditoolkit have?",
    "answer": "miditoolkit has version 0.1.16."
  }
]