[
  {
    "question": "What is the version of embedding_reader?",
    "answer": "The version of embedding_reader is 1.7.0."
  },
  {
    "question": "What version of embeddings is listed?",
    "answer": "The listed version for embeddings is 0.0.6."
  },
  {
    "question": "List all available versions for emcee.",
    "answer": "Available versions for emcee are 3.1.6, 3.1.4, 3.1.3, and 3.0.2."
  },
  {
    "question": "What is the latest version of emcee?",
    "answer": "The latest version of emcee is 3.1.6."
  },
  {
    "question": "Does emcee have a 3.0.2 version?",
    "answer": "Yes, emcee has a 3.0.2 version."
  },
  {
    "question": "What version of emmet is available?",
    "answer": "The available version for emmet is 2018.6.7."
  },
  {
    "question": "What are the versions of emmet_core?",
    "answer": "The versions of emmet_core are 0.69.11 and 0.68.0."
  },
  {
    "question": "Is version 0.69.11 available for emmet_core?",
    "answer": "Yes, version 0.69.11 is available for emmet_core."
  },
  {
    "question": "Which versions of emoji are listed?",
    "answer": "The listed versions for emoji are 1.4.1 and 0.5.2."
  },
  {
    "question": "What is the version for emu_base?",
    "answer": "The version for emu_base is 2.3.0."
  },
  {
    "question": "What version does emu_mps have?",
    "answer": "emu_mps has version 2.3.0."
  },
  {
    "question": "Provide the version of emu_sv.",
    "answer": "The version of emu_sv is 2.3.0."
  },
  {
    "question": "What is the energyscope version?",
    "answer": "The energyscope version is 1.0.1."
  },
  {
    "question": "What version of enlighten is listed?",
    "answer": "enlighten is listed with version 1.14.1."
  },
  {
    "question": "What is the version of enscons?",
    "answer": "The version of enscons is 0.28.0."
  },
  {
    "question": "What version of entrypoint2 is shown?",
    "answer": "entrypoint2 is shown with version 0.2.3."
  },
  {
    "question": "What are the available versions for entrypoints?",
    "answer": "The available versions for entrypoints are 0.4, 0.3, and 0.2.3."
  },
  {
    "question": "List the versions for enum34.",
    "answer": "The versions for enum34 are 1.1.10 and 1.1.6."
  },
  {
    "question": "What is the version of envpool?",
    "answer": "The version of envpool is 0.8.1."
  },
  {
    "question": "What versions of ephem are available?",
    "answer": "ephem has versions 4.1.4 and 4.1.3."
  },
  {
    "question": "What is the version of EQTransformer?",
    "answer": "EQTransformer is version 0.1.59."
  },
  {
    "question": "Provide a list of all equinox versions.",
    "answer": "All equinox versions are 0.13.0, 0.11.9, 0.11.3, and 0.10.11."
  },
  {
    "question": "What is the version of esm?",
    "answer": "esm is version 3.0.4."
  },
  {
    "question": "List the versions of et_xmlfile.",
    "answer": "The versions of et_xmlfile are 2.0.0, 1.1.0, and 1.0.1."
  },
  {
    "question": "What are the available versions for ete3?",
    "answer": "The available versions for ete3 are 3.1.3, 3.1.2, and 3.1.1."
  },
  {
    "question": "What is the latest version of etils?",
    "answer": "The latest version of etils is 1.13.0."
  },
  {
    "question": "List some versions of etils.",
    "answer": "Some versions of etils include 1.13.0, 1.12.2, and 1.12.0."
  },
  {
    "question": "What is the version of etuples?",
    "answer": "The version of etuples is 0.3.5."
  },
  {
    "question": "What version of EukRep is available?",
    "answer": "EukRep is available in version 0.6.5."
  },
  {
    "question": "What is the version of eval_type_backport?",
    "answer": "The version of eval_type_backport is 0.2.0."
  },
  {
    "question": "What versions of evaluate are listed?",
    "answer": "The listed versions for evaluate are 0.4.3, 0.4.2, and 0.4.0."
  },
  {
    "question": "What is the version of evdev?",
    "answer": "The version of evdev is 1.4.0."
  },
  {
    "question": "List the versions available for everett.",
    "answer": "The versions available for everett are 3.3.0, 3.1.0, 2.0.1, and 1.0.2."
  },
  {
    "question": "What are the versions of evosax?",
    "answer": "The versions of evosax are 0.1.6 and 0.1.4."
  },
  {
    "question": "Does exceptiongroup have a 1.3.0 version?",
    "answer": "Yes, exceptiongroup has a 1.3.0 version."
  },
  {
    "question": "List the versions for exceptiongroup.",
    "answer": "The versions for exceptiongroup are 1.3.0, 1.2.2, 1.2.1, 1.1.3, 1.1.2, 1.1.1, and 1.1.0."
  },
  {
    "question": "What are the available versions for execnet?",
    "answer": "execnet has versions 2.1.1, 2.0.2, 1.9.0, and 1.7.1."
  },
  {
    "question": "List some versions of executing.",
    "answer": "Some versions of executing are 2.2.1, 2.2.0, and 2.1.0."
  },
  {
    "question": "What is the version of ExifRead_nocycle?",
    "answer": "The version of ExifRead_nocycle is 3.0.1."
  },
  {
    "question": "What versions of exoplanet are there?",
    "answer": "exoplanet has versions 0.6.0 and 0.5.3."
  },
  {
    "question": "List the versions for exoplanet_core.",
    "answer": "The versions for exoplanet_core are 0.2.0 and 0.1.2."
  },
  {
    "question": "What is the version of exotic_ld?",
    "answer": "exotic_ld is version 3.2.0."
  },
  {
    "question": "What is the version for exouprf?",
    "answer": "The version for exouprf is 1.0.1."
  },
  {
    "question": "What version of expecttest is listed?",
    "answer": "expecttest is listed with version 0.1.3."
  },
  {
    "question": "What are the available versions of extension_helpers?",
    "answer": "The available versions of extension_helpers are 1.4.0, 1.2.0, 1.1.1, 1.1.0, 1.0.0, and 0.1."
  },
  {
    "question": "What version does extern have?",
    "answer": "extern has version 0.4.1."
  },
  {
    "question": "What is the version of fabio?",
    "answer": "The version of fabio is 0.13.0."
  },
  {
    "question": "What version of fabric is available?",
    "answer": "fabric is available in version 3.2.2."
  },
  {
    "question": "What is the version of facexlib?",
    "answer": "The version of facexlib is 0.3.0."
  },
  {
    "question": "What version of fair_esm is listed?",
    "answer": "fair_esm is listed with version 2.0.0."
  },
  {
    "question": "List the versions for fairscale.",
    "answer": "The versions for fairscale are 0.4.13, 0.4.12, and 0.4.1."
  },
  {
    "question": "What version of fairseq is available?",
    "answer": "fairseq is available in version 0.12.2."
  },
  {
    "question": "What are the versions of fairseq2?",
    "answer": "The versions of fairseq2 are 0.4.5, 0.2.0, and 0.1.1."
  }
]