[
  {
    "question": "What is XGBoost?",
    "answer": "XGBoost is an optimized distributed gradient boosting library designed to be highly efficient, flexible and portable."
  },
  {
    "question": "What kind of tasks is XGBoost used for?",
    "answer": "It is a popular package used for a wide variety of machine learning and datascience tasks, serving the role of a convenient, domain-agnostic black box classifier."
  },
  {
    "question": "Does XGBoost support GPU acceleration?",
    "answer": "XGBoost provides GPU accelerated learning for some problems, and Compute Canada provides a GPU enabled build."
  },
  {
    "question": "Where can I find detailed documentation for XGBoost?",
    "answer": "For detailed documentation on using the library, please consult the xgboost documentation."
  },
  {
    "question": "Is there specific documentation for GPU-enabled training with XGBoost?",
    "answer": "Yes, there is a separate section for GPU-enabled training in the xgboost documentation."
  },
  {
    "question": "What is a common way to use XGBoost?",
    "answer": "A very common way to use XGBoost is though its python interface, provided as the `xgboost` python module."
  },
  {
    "question": "How does Compute Canada provide the XGBoost Python module?",
    "answer": "Compute Canada provides an optimized, multi-GPU enabled build as a Python wheel."
  },
  {
    "question": "What should users do before starting an XGBoost project in Python?",
    "answer": "Readers should familiarize themselves with the use of Python virtual environments before starting an XGBoost project."
  },
  {
    "question": "Which version of XGBoost is currently available according to the document?",
    "answer": "Currently, version 0.81 of XGBoost is available."
  },
  {
    "question": "What are the commands to install XGBoost 0.81 in a Python virtual environment?",
    "answer": "First, load modules: `module load nixpkgs/16.09 intel/2018.3 cuda/10.0.130` and `module load nccl/2.3.5`. Then, install with pip: `pip install xgboost==0.81 --no-index`."
  }
]